{"model":"composite_linear_logit","run_id":"SRKW_r4_W_19700101_20241231_v_1_0_2","resolution":4,"year":2025,"stat_week":32,"rows":[{"feature":"spatiotemporal_climatology_prob__log","mean_abs_phi_logit":0.9398094391385501,"mean_phi_logit":0.07864255001515828},{"feature":"exponential_smoothing_prob__log","mean_abs_phi_logit":0.18299691336338267,"mean_phi_logit":6.579099405186112e-17},{"feature":"prior_period_lag52_p1_prob","mean_abs_phi_logit":0.17557690718069527,"mean_phi_logit":0.019147274804389297},{"feature":"DIST_TO_SHORE_KM_LOG1P","mean_abs_phi_logit":0.16251306067598006,"mean_phi_logit":-3.5089446124867996e-08},{"feature":"WATER_INDEX","mean_abs_phi_logit":0.1227780162747734,"mean_phi_logit":-9.156161253056052e-10},{"feature":"neighbor_climatology_prob__sqrt","mean_abs_phi_logit":0.08855211900819566,"mean_phi_logit":-7.401486830834377e-18},{"feature":"spatiotemporal_climatology__prior_10_yr_p1_prob","mean_abs_phi_logit":0.08572609875852495,"mean_phi_logit":-0.008608958243815088},{"feature":"spatiotemporal_climatology__all_time_prob","mean_abs_phi_logit":0.07939680140251819,"mean_phi_logit":0.024436117494136482},{"feature":"spatial_climatology__all_time_p1_prob","mean_abs_phi_logit":0.07835698209755522,"mean_phi_logit":-8.223874256482641e-19},{"feature":"spatial_climatology__prior_10_yr_p1_prob","mean_abs_phi_logit":0.0762214963312689,"mean_phi_logit":-8.223874256482641e-19},{"feature":"spatiotemporal_climatology__prior_10_yr_prob","mean_abs_phi_logit":0.06388782081508153,"mean_phi_logit":0.005823894120967703},{"feature":"spatiotemporal_climatology__prior_5_yr_prob","mean_abs_phi_logit":0.06348232882879923,"mean_phi_logit":-0.0064493538816863824},{"feature":"exponential_smoothing__prior_5_yr_prob","mean_abs_phi_logit":0.06300189330220766,"mean_phi_logit":-3.2895497025930565e-18},{"feature":"exponential_smoothing__prior_10_yr_prob","mean_abs_phi_logit":0.06220606486314342,"mean_phi_logit":-3.2895497025930565e-18},{"feature":"exponential_smoothing__all_time_prob","mean_abs_phi_logit":0.0517653841125589,"mean_phi_logit":-3.2895497025930565e-18},{"feature":"TOTAL_SHORELINE_KM","mean_abs_phi_logit":0.051510283427594776,"mean_phi_logit":1.702174729973833e-09},{"feature":"spatial_climatology__prior_5_yr_p1_prob","mean_abs_phi_logit":0.04515834980197188,"mean_phi_logit":2.4671622769447924e-18},{"feature":"prior_period_lag8_prob","mean_abs_phi_logit":0.04422205718079023,"mean_phi_logit":-0.04422205718079023},{"feature":"spatiotemporal_climatology__prior_5_yr_p1_prob","mean_abs_phi_logit":0.04106367551109042,"mean_phi_logit":-0.0003499123626522987},{"feature":"exponential_smoothing__all_time_p1_prob","mean_abs_phi_logit":0.03704591504757354,"mean_phi_logit":2.8783559897689243e-18},{"feature":"exponential_smoothing__prior_5_yr_p1_prob","mean_abs_phi_logit":0.03390158336565288,"mean_phi_logit":4.1119371282413207e-19},{"feature":"exponential_smoothing__prior_10_yr_p1_prob","mean_abs_phi_logit":0.03390158336565284,"mean_phi_logit":2.4671622769447924e-18},{"feature":"prior_period_lag4_prob","mean_abs_phi_logit":0.03229060209958392,"mean_phi_logit":0.002235895225607932},{"feature":"neighbor_climatology__all_time_prob","mean_abs_phi_logit":0.02676605627254916,"mean_phi_logit":1.6447748512965283e-18},{"feature":"neighbor_climatology__prior_10_yr_prob","mean_abs_phi_logit":0.026402094556513454,"mean_phi_logit":-2.05596856412066e-18},{"feature":"rolling_mean_w8_prob","mean_abs_phi_logit":0.025918184906266815,"mean_phi_logit":-0.01187971614287969},{"feature":"spatiotemporal_climatology__prior_10_yr_p2_prob","mean_abs_phi_logit":0.024790641911202314,"mean_phi_logit":0.006780474401210416},{"feature":"spatial_climatology__all_time_prob","mean_abs_phi_logit":0.02360306463024281,"mean_phi_logit":-8.223874256482641e-19},{"feature":"prior_period_lag2_p1_prob","mean_abs_phi_logit":0.021119853328155944,"mean_phi_logit":-0.021119853328155944},{"feature":"seasonal_alignment_error__prior_5_yr_p1_prob","mean_abs_phi_logit":0.01737207356452331,"mean_phi_logit":0.005649713896088278},{"feature":"seasonal_alignment_error__prior_10_yr_p1_prob","mean_abs_phi_logit":0.0173720735645233,"mean_phi_logit":0.005649713896088276},{"feature":"seasonal_alignment_error__all_time_p1_prob","mean_abs_phi_logit":0.01737207356452168,"mean_phi_logit":0.005649713896087748},{"feature":"rolling_mean_w8_p1_prob","mean_abs_phi_logit":0.016635879805516292,"mean_phi_logit":-0.006155375293404953},{"feature":"PCT_WATER","mean_abs_phi_logit":0.016574045770769746,"mean_phi_logit":-6.942432637513785e-10},{"feature":"spatial_climatology__prior_10_yr_prob","mean_abs_phi_logit":0.016256867090675482,"mean_phi_logit":4.1119371282413207e-19},{"feature":"seasonal_alignment_error__prior_10_yr_prob","mean_abs_phi_logit":0.016042234953048032,"mean_phi_logit":0.0034728418903994212},{"feature":"seasonal_alignment_error__all_time_prob","mean_abs_phi_logit":0.016042234952837475,"mean_phi_logit":0.0034728418903538366},{"feature":"seasonal_alignment_error__prior_5_yr_prob","mean_abs_phi_logit":0.01604223495281317,"mean_phi_logit":0.003472841890348575},{"feature":"rolling_mean_w2_p1_prob","mean_abs_phi_logit":0.01593679214964037,"mean_phi_logit":-0.01593679214964037},{"feature":"clim_eras__prior_10_yr_prob","mean_abs_phi_logit":0.014873612080565809,"mean_phi_logit":-0.0012327220404211095},{"feature":"clim_eras__prior_5_yr_prob","mean_abs_phi_logit":0.014873612080565809,"mean_phi_logit":-0.0012327220404211095},{"feature":"clim_eras__all_time_prob","mean_abs_phi_logit":0.014873612080565791,"mean_phi_logit":-0.001232722040421107},{"feature":"clim_roll_5y__all_time_prob","mean_abs_phi_logit":0.013200493677367132,"mean_phi_logit":-4.1119371282413207e-19},{"feature":"clim_roll_5y__prior_10_yr_prob","mean_abs_phi_logit":0.013200493677367128,"mean_phi_logit":4.1119371282413207e-19},{"feature":"clim_roll_5y__prior_5_yr_prob","mean_abs_phi_logit":0.013200493677367128,"mean_phi_logit":4.1119371282413207e-19},{"feature":"rolling_mean_w3_p1_prob","mean_abs_phi_logit":0.012532584399851802,"mean_phi_logit":-0.006383847596572378},{"feature":"rolling_mean_w5_p1_prob","mean_abs_phi_logit":0.012305097341927546,"mean_phi_logit":-0.005370240057469228},{"feature":"seasonal_alignment_error__all_time_p2_prob","mean_abs_phi_logit":0.011356727041090087,"mean_phi_logit":-0.0070728221956442095},{"feature":"seasonal_alignment_error__prior_5_yr_p2_prob","mean_abs_phi_logit":0.011356727041087191,"mean_phi_logit":-0.007072822195642408},{"feature":"seasonal_alignment_error__prior_10_yr_p2_prob","mean_abs_phi_logit":0.011356727041075383,"mean_phi_logit":-0.0070728221956350545},{"feature":"rolling_mean_w1_p1_prob","mean_abs_phi_logit":0.010916350763166478,"mean_phi_logit":-0.010916350763166478},{"feature":"prior_period_lag1_p1_prob","mean_abs_phi_logit":0.010916350763166476,"mean_phi_logit":-0.010916350763166476},{"feature":"spatiotemporal_neighbor_climatology__prior_10_yr_prob","mean_abs_phi_logit":0.010904265998495742,"mean_phi_logit":-0.0010728462939087245},{"feature":"spatiotemporal_climatology__all_time_p1_prob","mean_abs_phi_logit":0.010782597998190497,"mean_phi_logit":-0.003090758825564091},{"feature":"prior_period_lag1_prob","mean_abs_phi_logit":0.010354273587290692,"mean_phi_logit":-0.010354273587290692},{"feature":"rolling_mean_w1_prob","mean_abs_phi_logit":0.010354273587290685,"mean_phi_logit":-0.010354273587290685},{"feature":"rolling_mean_w4_p1_prob","mean_abs_phi_logit":0.00987534284094468,"mean_phi_logit":-0.0031604101160147145},{"feature":"rolling_mean_w2_prob","mean_abs_phi_logit":0.009404217028592857,"mean_phi_logit":-0.009404217028592857},{"feature":"spatiotemporal_neighbor_climatology__all_time_prob","mean_abs_phi_logit":0.009184759655133747,"mean_phi_logit":0.0029498835383749444},{"feature":"prior_period_lag52_prob","mean_abs_phi_logit":0.009076504415483817,"mean_phi_logit":-0.004656649430212842},{"feature":"prior_period_lag2_prob","mean_abs_phi_logit":0.008403225111366694,"mean_phi_logit":-0.008403225111366694},{"feature":"spatial_climatology__prior_5_yr_p2_prob","mean_abs_phi_logit":0.008338085689124948,"mean_phi_logit":5.653913551331816e-19},{"feature":"neighbor_climatology__prior_5_yr_prob","mean_abs_phi_logit":0.008308387173379292,"mean_phi_logit":2.0559685641206603e-19},{"feature":"prior_period_lag2_p2_prob","mean_abs_phi_logit":0.008182667074889951,"mean_phi_logit":-0.008182667074889951},{"feature":"rolling_mean_w3_prob","mean_abs_phi_logit":0.008141400343265704,"mean_phi_logit":-0.0033087980366814573},{"feature":"exponential_smoothing__all_time_p2_prob","mean_abs_phi_logit":0.007696389670711869,"mean_phi_logit":-1.0279842820603302e-19},{"feature":"exponential_smoothing__prior_10_yr_p2_prob","mean_abs_phi_logit":0.007504564345099918,"mean_phi_logit":2.569960705150825e-19},{"feature":"exponential_smoothing__prior_5_yr_p2_prob","mean_abs_phi_logit":0.007504564345099894,"mean_phi_logit":-2.0559685641206603e-19},{"feature":"spatial_climatology__prior_10_yr_p2_prob","mean_abs_phi_logit":0.007465773663490831,"mean_phi_logit":5.139921410301651e-20},{"feature":"spatiotemporal_climatology__all_time_p2_prob","mean_abs_phi_logit":0.006646320629269173,"mean_phi_logit":0.0030278326588934284},{"feature":"neighbor_climatology__prior_10_yr_p1_prob","mean_abs_phi_logit":0.0065955766257841135,"mean_phi_logit":-3.5979449872111554e-19},{"feature":"neighbor_climatology__all_time_p1_prob","mean_abs_phi_logit":0.006320392720621709,"mean_phi_logit":-4.625929269271486e-19},{"feature":"spatiotemporal_neighbor_climatology__all_time_p2_prob","mean_abs_phi_logit":0.0059562556647866005,"mean_phi_logit":0.0037585161129863186},{"feature":"rolling_mean_w8_p2_prob","mean_abs_phi_logit":0.00580437786055874,"mean_phi_logit":-0.00208865613205472},{"feature":"spatiotemporal_neighbor_climatology__prior_5_yr_p1_prob","mean_abs_phi_logit":0.005794468418770613,"mean_phi_logit":0.00015862788111748504},{"feature":"spatiotemporal_neighbor_climatology__prior_5_yr_p2_prob","mean_abs_phi_logit":0.005668668403161897,"mean_phi_logit":0.0005909663736488536},{"feature":"spatiotemporal_neighbor_climatology__prior_5_yr_prob","mean_abs_phi_logit":0.005142991307064229,"mean_phi_logit":-0.0006283931274368705},{"feature":"rolling_mean_w2_p2_prob","mean_abs_phi_logit":0.00511391167733247,"mean_phi_logit":-0.00511391167733247},{"feature":"prior_period_lag4_p1_prob","mean_abs_phi_logit":0.004949661770693561,"mean_phi_logit":-0.00019146743657421213},{"feature":"rolling_mean_w5_p2_prob","mean_abs_phi_logit":0.004761969419962555,"mean_phi_logit":-0.0014345128132966754},{"feature":"spatiotemporal_climatology_prob__x__rolling_mean_w4_prob","mean_abs_phi_logit":0.004712397653847852,"mean_phi_logit":0.0010732275214629303},{"feature":"spatiotemporal_climatology__prior_5_yr_p2_prob","mean_abs_phi_logit":0.0046891308815598725,"mean_phi_logit":0.00047202397839232686},{"feature":"spatiotemporal_neighbor_climatology__prior_10_yr_p2_prob","mean_abs_phi_logit":0.004667821878012302,"mean_phi_logit":0.001964181923391929},{"feature":"prior_period_lag52_p2_prob","mean_abs_phi_logit":0.004428088299655941,"mean_phi_logit":-0.00043283601150842955},{"feature":"spatiotemporal_neighbor_climatology__all_time_p1_prob","mean_abs_phi_logit":0.004054600992266559,"mean_phi_logit":0.0014813786698122252},{"feature":"rolling_mean_w3_p2_prob","mean_abs_phi_logit":0.0038131313891314484,"mean_phi_logit":-0.0014905089858992572},{"feature":"rolling_mean_w4_p2_prob","mean_abs_phi_logit":0.003670509609718261,"mean_phi_logit":-0.0005735502038825926},{"feature":"clim_decay_hl3y__prior_10_yr_prob","mean_abs_phi_logit":0.0036498471225105637,"mean_phi_logit":-1.3407588819453333e-07},{"feature":"clim_decay_hl3y__all_time_prob","mean_abs_phi_logit":0.0036498471225105598,"mean_phi_logit":-1.3407588819443052e-07},{"feature":"clim_decay_hl3y__prior_5_yr_prob","mean_abs_phi_logit":0.0036498471225105515,"mean_phi_logit":-1.340758881946875e-07},{"feature":"neighbor_climatology__prior_5_yr_p2_prob","mean_abs_phi_logit":0.003008551981372992,"mean_phi_logit":-1.413478387832954e-19},{"feature":"spatial_climatology__all_time_p2_prob","mean_abs_phi_logit":0.0028510044643734116,"mean_phi_logit":2.248715617006972e-19},{"feature":"spatial_climatology__prior_5_yr_prob","mean_abs_phi_logit":0.0023787030884236185,"mean_phi_logit":5.139921410301651e-20},{"feature":"neighbor_climatology__all_time_p2_prob","mean_abs_phi_logit":0.0022175367385626333,"mean_phi_logit":-3.4694469519536144e-19},{"feature":"prior_period_lag1_p2_prob","mean_abs_phi_logit":0.0021223197308919877,"mean_phi_logit":-0.0021223197308919877},{"feature":"rolling_mean_w1_p2_prob","mean_abs_phi_logit":0.0021223197308919764,"mean_phi_logit":-0.0021223197308919764},{"feature":"neighbor_climatology__prior_10_yr_p2_prob","mean_abs_phi_logit":0.0021203719313810194,"mean_phi_logit":-3.4051979343248437e-19},{"feature":"DIST_TO_SHORE_KM","mean_abs_phi_logit":0.0019470089007181239,"mean_phi_logit":-6.825667311453435e-11},{"feature":"prior_period_lag4_p2_prob","mean_abs_phi_logit":0.0015597782870091894,"mean_phi_logit":0.00037801510707708146},{"feature":"rolling_mean_w4_prob__x__neighbor_climatology_prob","mean_abs_phi_logit":0.0014233384439949247,"mean_phi_logit":7.986759478579155e-05},{"feature":"neighbor_climatology_prob__x__rolling_mean_w4_prob","mean_abs_phi_logit":0.0014233384439949245,"mean_phi_logit":7.986759478579157e-05},{"feature":"streak_features__all_time_prob","mean_abs_phi_logit":0.0011104178240267319,"mean_phi_logit":-0.0011104178240267319},{"feature":"streak_features__prior_10_yr_prob","mean_abs_phi_logit":0.0011104178240267269,"mean_phi_logit":-0.0011104178240267269},{"feature":"streak_features__prior_5_yr_prob","mean_abs_phi_logit":0.001110417824026724,"mean_phi_logit":-0.001110417824026724},{"feature":"rolling_mean_w52_prob","mean_abs_phi_logit":0.0008557486737274256,"mean_phi_logit":-2.8111785978836574e-06},{"feature":"neighbor_climatology__prior_5_yr_p1_prob","mean_abs_phi_logit":0.0007594423357579082,"mean_phi_logit":1.927470528863119e-20},{"feature":"spatiotemporal_neighbor_climatology__prior_10_yr_p1_prob","mean_abs_phi_logit":0.0006765804187933376,"mean_phi_logit":9.809883604629981e-05},{"feature":"neighbor_climatology_prob__x__spatiotemporal_neighbor_climatology_prob","mean_abs_phi_logit":0.0006187253947980391,"mean_phi_logit":-0.00019853078042847592},{"feature":"spatiotemporal_neighbor_climatology_prob__x__rolling_mean_w4_prob","mean_abs_phi_logit":0.0006112519010151007,"mean_phi_logit":0.00014756923576455687},{"feature":"lag_vector_features__prior_10_yr_prob","mean_abs_phi_logit":0.0004256283089523109,"mean_phi_logit":-0.0004256283089523109},{"feature":"lag_vector_features__prior_5_yr_prob","mean_abs_phi_logit":0.00042562830895231013,"mean_phi_logit":-0.00042562830895231013},{"feature":"lag_vector_features__all_time_prob","mean_abs_phi_logit":0.0004256283089523078,"mean_phi_logit":-0.0004256283089523078},{"feature":"lag_vector_features__all_time_p1_prob","mean_abs_phi_logit":0.0003788282769900505,"mean_phi_logit":-0.0003788282769900505},{"feature":"lag_vector_features__prior_10_yr_p1_prob","mean_abs_phi_logit":0.0003788282769900494,"mean_phi_logit":-0.0003788282769900494},{"feature":"lag_vector_features__prior_5_yr_p1_prob","mean_abs_phi_logit":0.0003788282769900494,"mean_phi_logit":-0.0003788282769900494},{"feature":"lagged_neighbor_presence__all_time_prob","mean_abs_phi_logit":0.0003030618557516573,"mean_phi_logit":-0.0003030618557516573},{"feature":"lagged_neighbor_presence__prior_5_yr_prob","mean_abs_phi_logit":0.0003030618557516571,"mean_phi_logit":-0.0003030618557516571},{"feature":"lagged_neighbor_presence__prior_10_yr_prob","mean_abs_phi_logit":0.00030306185575165615,"mean_phi_logit":-0.00030306185575165615},{"feature":"streak_features__prior_10_yr_p2_prob","mean_abs_phi_logit":0.0002572006636500415,"mean_phi_logit":0.0002572006636500415},{"feature":"streak_features__prior_5_yr_p2_prob","mean_abs_phi_logit":0.00025720066365003945,"mean_phi_logit":0.00025720066365003945},{"feature":"streak_features__all_time_p2_prob","mean_abs_phi_logit":0.00025720066365003826,"mean_phi_logit":0.00025720066365003826},{"feature":"rolling_mean_w4_prob","mean_abs_phi_logit":0.00013289560474928822,"mean_phi_logit":-4.017587287588216e-05},{"feature":"streak_features__prior_5_yr_p1_prob","mean_abs_phi_logit":5.116172755807366e-05,"mean_phi_logit":5.116172755807366e-05},{"feature":"streak_features__all_time_p1_prob","mean_abs_phi_logit":5.1161727558072965e-05,"mean_phi_logit":5.1161727558072965e-05},{"feature":"streak_features__prior_10_yr_p1_prob","mean_abs_phi_logit":5.1161727558072024e-05,"mean_phi_logit":5.1161727558072024e-05},{"feature":"lag_vector_features__prior_5_yr_p2_prob","mean_abs_phi_logit":4.8798490649552586e-05,"mean_phi_logit":-4.8798490649552586e-05},{"feature":"lag_vector_features__all_time_p2_prob","mean_abs_phi_logit":4.8798490649552545e-05,"mean_phi_logit":-4.8798490649552545e-05},{"feature":"lag_vector_features__prior_10_yr_p2_prob","mean_abs_phi_logit":4.8798490649552314e-05,"mean_phi_logit":-4.8798490649552314e-05},{"feature":"delta_features__prior_5_yr_prob","mean_abs_phi_logit":2.6044298079717024e-05,"mean_phi_logit":2.6044298079717024e-05},{"feature":"delta_features__all_time_prob","mean_abs_phi_logit":2.6044298079717014e-05,"mean_phi_logit":2.6044298079717014e-05},{"feature":"delta_features__prior_10_yr_prob","mean_abs_phi_logit":2.604429807971634e-05,"mean_phi_logit":2.604429807971634e-05},{"feature":"seasonal_climatology_prob__x__spatiotemporal_climatology_prob","mean_abs_phi_logit":1.8760888904105874e-05,"mean_phi_logit":8.359767830731734e-06},{"feature":"seasonal_climatology_prob__x__spatial_climatology_prob","mean_abs_phi_logit":4.928496012533215e-06,"mean_phi_logit":-1.5700506818551663e-06},{"feature":"seasonal_climatology_prob__x__rolling_mean_w4_prob","mean_abs_phi_logit":2.3392352790112464e-08,"mean_phi_logit":2.4527418166546717e-09},{"feature":"MONTH_OF_WEEK_START","mean_abs_phi_logit":0.0,"mean_phi_logit":0.0},{"feature":"seasonal_climatology__prior_5_yr_p1_prob","mean_abs_phi_logit":0.0,"mean_phi_logit":0.0},{"feature":"CONTAINS_MAJOR_HOLIDAY_WINDOW_CA","mean_abs_phi_logit":0.0,"mean_phi_logit":0.0},{"feature":"CONTAINS_MAJOR_HOLIDAY_WINDOW_MX","mean_abs_phi_logit":0.0,"mean_phi_logit":0.0},{"feature":"seasonal_climatology__all_time_p1_prob","mean_abs_phi_logit":0.0,"mean_phi_logit":0.0},{"feature":"seasonal_climatology__prior_10_yr_p1_prob","mean_abs_phi_logit":0.0,"mean_phi_logit":0.0},{"feature":"CONTAINS_MAJOR_HOLIDAY_MX","mean_abs_phi_logit":0.0,"mean_phi_logit":0.0},{"feature":"prior_period_lag3_p2_prob","mean_abs_phi_logit":0.0,"mean_phi_logit":0.0},{"feature":"seasonal_climatology__prior_10_yr_prob","mean_abs_phi_logit":0.0,"mean_phi_logit":0.0},{"feature":"seasonal_climatology__prior_5_yr_prob","mean_abs_phi_logit":0.0,"mean_phi_logit":0.0},{"feature":"seasonal_climatology__all_time_prob","mean_abs_phi_logit":0.0,"mean_phi_logit":0.0},{"feature":"prior_period_lag3_p1_prob","mean_abs_phi_logit":0.0,"mean_phi_logit":0.0},{"feature":"seasonal_climatology__all_time_p2_prob","mean_abs_phi_logit":0.0,"mean_phi_logit":0.0},{"feature":"seasonal_climatology__prior_5_yr_p2_prob","mean_abs_phi_logit":0.0,"mean_phi_logit":0.0},{"feature":"seasonal_climatology__prior_10_yr_p2_prob","mean_abs_phi_logit":0.0,"mean_phi_logit":0.0},{"feature":"CONTAINS_MAJOR_HOLIDAY_WINDOW_US","mean_abs_phi_logit":0.0,"mean_phi_logit":0.0},{"feature":"CONTAINS_MAJOR_HOLIDAY_CA","mean_abs_phi_logit":0.0,"mean_phi_logit":0.0},{"feature":"QUARTER_OF_WEEK_START","mean_abs_phi_logit":0.0,"mean_phi_logit":0.0},{"feature":"CONTAINS_HOLIDAY","mean_abs_phi_logit":0.0,"mean_phi_logit":0.0},{"feature":"prior_period_lag3_prob","mean_abs_phi_logit":0.0,"mean_phi_logit":0.0},{"feature":"WEEK_OF_MONTH","mean_abs_phi_logit":0.0,"mean_phi_logit":0.0},{"feature":"IS_YEAR_START_WEEK","mean_abs_phi_logit":0.0,"mean_phi_logit":0.0},{"feature":"IS_YEAR_END_WEEK","mean_abs_phi_logit":0.0,"mean_phi_logit":0.0},{"feature":"IS_MONTH_BOUNDARY_WEEK","mean_abs_phi_logit":0.0,"mean_phi_logit":0.0},{"feature":"SIN_STAT_WEEK","mean_abs_phi_logit":0.0,"mean_phi_logit":0.0},{"feature":"COS_STAT_WEEK","mean_abs_phi_logit":0.0,"mean_phi_logit":0.0},{"feature":"SIN_WEEK_CENTER_DOY","mean_abs_phi_logit":0.0,"mean_phi_logit":0.0},{"feature":"COS_WEEK_CENTER_DOY","mean_abs_phi_logit":0.0,"mean_phi_logit":0.0},{"feature":"HOLIDAY_COUNT_IN_WEEK","mean_abs_phi_logit":0.0,"mean_phi_logit":0.0},{"feature":"CONTAINS_MAJOR_HOLIDAY_US","mean_abs_phi_logit":0.0,"mean_phi_logit":0.0},{"feature":"CONTAINS_HOLIDAY_US","mean_abs_phi_logit":0.0,"mean_phi_logit":0.0},{"feature":"CONTAINS_HOLIDAY_CA","mean_abs_phi_logit":0.0,"mean_phi_logit":0.0},{"feature":"CONTAINS_HOLIDAY_MX","mean_abs_phi_logit":0.0,"mean_phi_logit":0.0},{"feature":"HOLIDAY_COUNT_IN_WEEK_US","mean_abs_phi_logit":0.0,"mean_phi_logit":0.0},{"feature":"HOLIDAY_COUNT_IN_WEEK_CA","mean_abs_phi_logit":0.0,"mean_phi_logit":0.0},{"feature":"HOLIDAY_COUNT_IN_WEEK_MX","mean_abs_phi_logit":0.0,"mean_phi_logit":0.0},{"feature":"CONTAINS_HOLIDAY_CUSTOM","mean_abs_phi_logit":0.0,"mean_phi_logit":0.0},{"feature":"HOLIDAY_COUNT_IN_WEEK_CUSTOM","mean_abs_phi_logit":0.0,"mean_phi_logit":0.0},{"feature":"CONTAINS_MAJOR_HOLIDAY_WINDOW","mean_abs_phi_logit":0.0,"mean_phi_logit":0.0},{"feature":"CONTAINS_MAJOR_HOLIDAY","mean_abs_phi_logit":0.0,"mean_phi_logit":0.0}]}