{
  "rows": [
    {"year": 2025, "period": 1, "stat_week": 1, "expected_count": 56, "lower_ci": 42, "upper_ci": 70, "typical_error": 14},
    {"year": 2025, "period": 2, "stat_week": 2, "expected_count": 62, "lower_ci": 46, "upper_ci": 78, "typical_error": 16},
    {"year": 2025, "period": 3, "stat_week": 3, "expected_count": 68, "lower_ci": 50, "upper_ci": 86, "typical_error": 18},
    {"year": 2025, "period": 4, "stat_week": 4, "expected_count": 74, "lower_ci": 54, "upper_ci": 94, "typical_error": 20},
    {"year": 2025, "period": 5, "stat_week": 5, "expected_count": 80, "lower_ci": 68, "upper_ci": 92, "typical_error": 12},
    {"year": 2025, "period": 6, "stat_week": 6, "expected_count": 52, "lower_ci": 38, "upper_ci": 66, "typical_error": 14},
    {"year": 2025, "period": 7, "stat_week": 7, "expected_count": 58, "lower_ci": 42, "upper_ci": 74, "typical_error": 16},
    {"year": 2025, "period": 8, "stat_week": 8, "expected_count": 64, "lower_ci": 46, "upper_ci": 82, "typical_error": 18},
    {"year": 2025, "period": 9, "stat_week": 9, "expected_count": 70, "lower_ci": 50, "upper_ci": 90, "typical_error": 20},
    {"year": 2025, "period": 10, "stat_week": 10, "expected_count": 76, "lower_ci": 64, "upper_ci": 88, "typical_error": 12},
    {"year": 2025, "period": 11, "stat_week": 11, "expected_count": 82, "lower_ci": 68, "upper_ci": 96, "typical_error": 14},
    {"year": 2025, "period": 12, "stat_week": 12, "expected_count": 74, "lower_ci": 58, "upper_ci": 90, "typical_error": 16},
    {"year": 2025, "period": 13, "stat_week": 13, "expected_count": 80, "lower_ci": 62, "upper_ci": 98, "typical_error": 18},
    {"year": 2025, "period": 14, "stat_week": 14, "expected_count": 86, "lower_ci": 66, "upper_ci": 106, "typical_error": 20},
    {"year": 2025, "period": 15, "stat_week": 15, "expected_count": 92, "lower_ci": 80, "upper_ci": 104, "typical_error": 12},
    {"year": 2025, "period": 16, "stat_week": 16, "expected_count": 98, "lower_ci": 84, "upper_ci": 112, "typical_error": 14},
    {"year": 2025, "period": 17, "stat_week": 17, "expected_count": 70, "lower_ci": 54, "upper_ci": 86, "typical_error": 16},
    {"year": 2025, "period": 18, "stat_week": 18, "expected_count": 76, "lower_ci": 58, "upper_ci": 94, "typical_error": 18},
    {"year": 2025, "period": 19, "stat_week": 19, "expected_count": 82, "lower_ci": 62, "upper_ci": 102, "typical_error": 20},
    {"year": 2025, "period": 20, "stat_week": 20, "expected_count": 112, "lower_ci": 100, "upper_ci": 124, "typical_error": 12},
    {"year": 2025, "period": 21, "stat_week": 21, "expected_count": 118, "lower_ci": 104, "upper_ci": 132, "typical_error": 14},
    {"year": 2025, "period": 22, "stat_week": 22, "expected_count": 124, "lower_ci": 108, "upper_ci": 140, "typical_error": 16},
    {"year": 2025, "period": 23, "stat_week": 23, "expected_count": 96, "lower_ci": 78, "upper_ci": 114, "typical_error": 18},
    {"year": 2025, "period": 24, "stat_week": 24, "expected_count": 102, "lower_ci": 82, "upper_ci": 122, "typical_error": 20},
    {"year": 2025, "period": 25, "stat_week": 25, "expected_count": 108, "lower_ci": 96, "upper_ci": 120, "typical_error": 12},
    {"year": 2025, "period": 26, "stat_week": 26, "expected_count": 114, "lower_ci": 100, "upper_ci": 128, "typical_error": 14},
    {"year": 2025, "period": 27, "stat_week": 27, "expected_count": 120, "lower_ci": 104, "upper_ci": 136, "typical_error": 16},
    {"year": 2025, "period": 28, "stat_week": 28, "expected_count": 126, "lower_ci": 108, "upper_ci": 144, "typical_error": 18},
    {"year": 2025, "period": 29, "stat_week": 29, "expected_count": 98, "lower_ci": 78, "upper_ci": 118, "typical_error": 20},
    {"year": 2025, "period": 30, "stat_week": 30, "expected_count": 104, "lower_ci": 92, "upper_ci": 116, "typical_error": 12},
    {"year": 2025, "period": 31, "stat_week": 31, "expected_count": 110, "lower_ci": 96, "upper_ci": 124, "typical_error": 14},
    {"year": 2025, "period": 32, "stat_week": 32, "expected_count": 116, "lower_ci": 100, "upper_ci": 132, "typical_error": 16},
    {"year": 2025, "period": 33, "stat_week": 33, "expected_count": 122, "lower_ci": 104, "upper_ci": 140, "typical_error": 18},
    {"year": 2025, "period": 34, "stat_week": 34, "expected_count": 94, "lower_ci": 74, "upper_ci": 114, "typical_error": 20},
    {"year": 2025, "period": 35, "stat_week": 35, "expected_count": 100, "lower_ci": 88, "upper_ci": 112, "typical_error": 12},
    {"year": 2025, "period": 36, "stat_week": 36, "expected_count": 106, "lower_ci": 92, "upper_ci": 120, "typical_error": 14},
    {"year": 2025, "period": 37, "stat_week": 37, "expected_count": 112, "lower_ci": 96, "upper_ci": 128, "typical_error": 16},
    {"year": 2025, "period": 38, "stat_week": 38, "expected_count": 118, "lower_ci": 100, "upper_ci": 136, "typical_error": 18},
    {"year": 2025, "period": 39, "stat_week": 39, "expected_count": 100, "lower_ci": 80, "upper_ci": 120, "typical_error": 20},
    {"year": 2025, "period": 40, "stat_week": 40, "expected_count": 72, "lower_ci": 60, "upper_ci": 84, "typical_error": 12},
    {"year": 2025, "period": 41, "stat_week": 41, "expected_count": 78, "lower_ci": 64, "upper_ci": 92, "typical_error": 14},
    {"year": 2025, "period": 42, "stat_week": 42, "expected_count": 84, "lower_ci": 68, "upper_ci": 100, "typical_error": 16},
    {"year": 2025, "period": 43, "stat_week": 43, "expected_count": 90, "lower_ci": 72, "upper_ci": 108, "typical_error": 18},
    {"year": 2025, "period": 44, "stat_week": 44, "expected_count": 96, "lower_ci": 76, "upper_ci": 116, "typical_error": 20},
    {"year": 2025, "period": 45, "stat_week": 45, "expected_count": 102, "lower_ci": 90, "upper_ci": 114, "typical_error": 12},
    {"year": 2025, "period": 46, "stat_week": 46, "expected_count": 54, "lower_ci": 40, "upper_ci": 68, "typical_error": 14},
    {"year": 2025, "period": 47, "stat_week": 47, "expected_count": 60, "lower_ci": 44, "upper_ci": 76, "typical_error": 16},
    {"year": 2025, "period": 48, "stat_week": 48, "expected_count": 66, "lower_ci": 48, "upper_ci": 84, "typical_error": 18},
    {"year": 2025, "period": 49, "stat_week": 49, "expected_count": 72, "lower_ci": 52, "upper_ci": 92, "typical_error": 20},
    {"year": 2025, "period": 50, "stat_week": 50, "expected_count": 78, "lower_ci": 66, "upper_ci": 90, "typical_error": 12},
    {"year": 2025, "period": 51, "stat_week": 51, "expected_count": 50, "lower_ci": 36, "upper_ci": 64, "typical_error": 14},
    {"year": 2025, "period": 52, "stat_week": 52, "expected_count": 56, "lower_ci": 40, "upper_ci": 72, "typical_error": 16},
    {"year": 2026, "period": 1, "stat_week": 1, "expected_count": 62, "lower_ci": 44, "upper_ci": 80, "typical_error": 18},
    {"year": 2026, "period": 2, "stat_week": 2, "expected_count": 68, "lower_ci": 48, "upper_ci": 88, "typical_error": 20},
    {"year": 2026, "period": 3, "stat_week": 3, "expected_count": 74, "lower_ci": 62, "upper_ci": 86, "typical_error": 12},
    {"year": 2026, "period": 4, "stat_week": 4, "expected_count": 80, "lower_ci": 66, "upper_ci": 94, "typical_error": 14},
    {"year": 2026, "period": 5, "stat_week": 5, "expected_count": 52, "lower_ci": 36, "upper_ci": 68, "typical_error": 16}
  ]
}
